fastprof/__init__.py
fastprof/base.py
fastprof/calculators.py
fastprof/channels.py
fastprof/core.py
fastprof/fit_data.py
fastprof/minimizers.py
fastprof/model_tools.py
fastprof/norms.py
fastprof/sample.py
fastprof/samplers.py
fastprof/sampling.py
fastprof/scans.py
fastprof/test_statistics.py
fastprof_import/__init__.py
fastprof_import/convert_pyhf.py
fastprof_import/convert_ws.py
fastprof_import/fit_ws.py
fastprof_import/inspect_ws.py
fastprof_import/tools.py
fastprof_utils/__init__.py
fastprof_utils/check_model.py
fastprof_utils/collect_results.py
fastprof_utils/compute_fast_limits.py
fastprof_utils/compute_limits.py
fastprof_utils/dump_debug.py
fastprof_utils/dump_samples.py
fastprof_utils/fit_fast.py
fastprof_utils/iterate.py
fastprof_utils/merge_channels.py
fastprof_utils/merge_models.py
fastprof_utils/plot.py
fastprof_utils/plot_valid.py
fastprof_utils/poi_scan.py
fastprof_utils/prune_nps.py
fastprof_utils/reparam.py
fastprof_utils/submit_limit.py
fastprof_utils/tools.py
fastprof-0.3.3.dist-info/LICENSE
fastprof-0.3.3.dist-info/METADATA
fastprof-0.3.3.dist-info/WHEEL
fastprof-0.3.3.dist-info/entry_points.txt
fastprof-0.3.3.dist-info/top_level.txt
fastprof-0.3.3.dist-info/RECORD
