Metadata-Version: 2.1
Name: fastprof
Version: 0.3.3
Summary: 'A fast profiling tool for likelihood-based statistical analyses'
Home-page: https://github.com/fastprof-hep/fastprof
Author: N. Berger
Author-email: nberger@mail.cern.ch
License: UNKNOWN
Platform: UNKNOWN
Classifier: Programming Language :: Python :: 3
Requires-Python: >=3.6
License-File: LICENSE
Requires-Dist: numpy (>=1.19.5)
Requires-Dist: scipy (>=1.5.0)
Requires-Dist: pandas (>=1.1.0)
Requires-Dist: matplotlib (>=3.3.3)
Requires-Dist: sphinx-rtd-theme (>=0.5.1)
Requires-Dist: sphinx-argparse (>=0.2.5)
Requires-Dist: mock (>=4.0.3)
Requires-Dist: PyYAML (>=5.1)
